setup.py
simchain/__init__.py
simchain/base58.py
simchain/consensus.py
simchain/datatype.py
simchain/ecc.py
simchain/hdwallet.py
simchain/logger.py
simchain/merkletree.py
simchain/mnemonics.py
simchain/network.py
simchain/params.py
simchain/peer.py
simchain/vm.py
simchain/wallet.py
simchain.egg-info/PKG-INFO
simchain.egg-info/SOURCES.txt
simchain.egg-info/dependency_links.txt
simchain.egg-info/top_level.txt
simchain/lbc/__init__.py
simchain/lbc/lattice.py
simchain/lbc/lyus.py
simchain/lbc/utils.py