Metadata-Version: 1.0
Name: simchain
Version: 1.0.0
Summary: python blockchain simulator
Home-page: https://github.com/YaoyaoBae/simchain
Author: YAOYAO PEI
Author-email: yaoyao.bae@foxmail.com
License: Hubei Univeristy of Technology license
Platform: UNKNOWN
